{
  "name": "sia2024",
  "description": "A simplistic implementation of SIA 2024",
  "version": "0.1",
  "author": "saso-basic, christophwaibel",
  "id": "f5cd6a0b-c7f9-42c9-b58c-045640dfe65d",
  "include-files": ["sia2024.py"],
  "components": [
    {
      "class-name": "Sia2024",
      "name": "SIA 2024",
      "abbreviation": "sia2024",
      "description": "Default values for SIA 380.1",
      "category": "[hive]",
      "subcategory": "demand",
      "id": "99dd97f1-b633-44e9-866c-6b6dc3bb8ae0",
      "main-module": "sia2024",
      "main-function": "default_values",
      "inputs": [
        {"type": "json", "name": "room", "nick-name": "room", "description": "Room type according to sia2024. should be a dictionary containing all properties."},
        {"type": "float", "name": "area", "nick-name": "area", "description": "Area in m². If no input given, default values as from SIA2024:2015 are used."},
        {"type": "integer", "name": "month", "nick-name": "month", "description": "Time period", "default": 1},
        {"type": "string", "name": "season", "nick-name": "season", "description": "Season, either 'winter' or 'summer'."}
      ],
      "outputs": [
        {"type": "float", "name": "tau", "nick-name": "τ [h]", "description": "Zeitkonstante des Gebäudes [h] - time constant"},
        {"type": "float", "name": "theta_i", "nick-name": "θ_i [°C]", "description": "Raumlufttemperatur"},
        {"type": "float", "name": "t", "nick-name": "t [h]", "description": "Länge der Berechnungsperiode [h]"},
        {"type": "float", "name": "A_op", "nick-name": "A_op [m2]", "description": "Aussenwandfläche (opak) [m2]"},
        {"type": "float", "name": "A_w", "nick-name": "A_w [m2]", "description": "Fensterfläche [m2]"},
        {"type": "float", "name": "U_op", "nick-name": "U_op [W/(m2K)]", "description": "Wärmedurchgangskoeffizient Aussenwand [W/m2K] - U value opaque walls"},
        {"type": "float", "name": "U_w", "nick-name": "U_w [W/(m2K)]", "description": "Wärmedurchgangskoeffizient Fenster [W/m2K] - U value windows"},
        {"type": "float", "name": "Vdot_e", "nick-name": "V\u0307_e [m3/h]", "description": "Aussenluft-Volumenstrom [m3/h] - exterior air volume flow"},
        {"type": "float", "name": "Vdot_inf", "nick-name": "V\u0307_inf [m3/h]", "description": "Aussenluft-Volumenstrom durch Infiltration [m3/h] - infiltration air volume flow"},
        {"type": "float", "name": "eta_rec", "nick-name": "η_rec [-]", "description": "Nutzungsgrad der Wärmerückgewinnung [-]"},
        {"type": "float", "name": "phi_P", "nick-name": "φ_P [W]", "description": "Wärmeabgabe Personen [W] - heat release People "},
        {"type": "float", "name": "phi_L", "nick-name": "φ_L [W]", "description": "Wärmeabgabe Beleuchtung [W] - heat release Lightning "},
        {"type": "float", "name": "phi_A", "nick-name": "φ_G [W]", "description": "Wärmeabgabe Geräte [W] - heat release Appliances [W]"},
        {"type": "float", "name": "t_P", "nick-name": "t_P [h]", "description": "Vollaststunden Personen [h] - full load hours People"},
        {"type": "float", "name": "t_L", "nick-name": "t_L [h]", "description": "Vollaststunden Beleuchtung [h] - full load hours Lightning"},
        {"type": "float", "name": "t_A", "nick-name": "t_A [h]", "description": "Vollaststunden Geräte [h] - full load hours Appliances"},
        {"type": "float", "name": "g", "nick-name": "g [-]", "description": "g-Wert [-] - g-Value windows"},
        {"type": "float", "name": "f_sh", "nick-name": "f_sh [-]", "description": "Reduktionsfaktor solare Wärmeeinträge [-]"}]
    }
  ],
  "parameters": [
    {
      "class-name": "Sia2024RoomList_Standard",
      "name": "RoomsStandard",
      "abbreviation": "rooms_standard",
      "description": "A list of SIA2024 rooms, standard",
      "category": "[hive]",
      "subcategory": "demand",
      "id": "8903e11e-abba-4318-a9b2-6728e2999652",
      "parameter-type": "ValueList",
      "csv": "200123_SIA2024_Raumdaten_Standardwert.csv"
    },
    {
      "class-name": "Sia2024RoomList_Existing",
      "name": "RoomsExisting",
      "abbreviation": "rooms_existing",
      "description": "A list of SIA2024 rooms, existing",
      "category": "[hive]",
      "subcategory": "demand",
      "id": "fb83131c-5b8d-4432-8bba-5991bd4b3309",
      "parameter-type": "ValueList",
      "csv": "200123_SIA2024_Raumdaten_Bestand.csv"
    },
    {
      "class-name": "Sia2024RoomList_Ideal",
      "name": "RoomsIdeal",
      "abbreviation": "rooms_ideal",
      "description": "A list of SIA2024 rooms, ideal",
      "category": "[hive]",
      "subcategory": "demand",
      "id": "772400f7-ee9a-4e53-b33d-bf0d676f4249",
      "parameter-type": "ValueList",
      "csv": "200123_SIA2024_Raumdaten_Zielwert.csv"
    }
  ]
}